setup.cfg
setup.py
bandit/__init__.py
bandit/bandit.py
bandit/email.py
bandit/job.py
bandit/version.py
bandit/yhat_json.py
bandit/dashboards/image-with-tables.html
bandit/dashboards/raw-html.html
bandit/dashboards/single-table.html
bandit_cli.egg-info/PKG-INFO
bandit_cli.egg-info/SOURCES.txt
bandit_cli.egg-info/dependency_links.txt
bandit_cli.egg-info/requires.txt
bandit_cli.egg-info/top_level.txt