Metadata-Version: 1.0
Name: bandit-cli
Version: 0.3.0
Summary: Bandit client for Yhat (http://yhat.com/)
Home-page: https://github.com/yhat/yhat-client
Author: Greg Lamp
Author-email: greg@yhathq.com
License: BSD
Keywords: yhat,bandit
Platform: UNKNOWN
